classhoster/__init__.py
classhoster/launch.py
classhoster/__pycache__/__init__.cpython-311.pyc
classhoster/__pycache__/launch.cpython-311.pyc
classhoster/examples/example_classes.py
classhoster/examples/test_class_hoster.py
classhoster/examples/__pycache__/__init__.cpython-311.pyc
classhoster/examples/__pycache__/example_classes.cpython-311.pyc
classhoster/main/client.py
classhoster/main/gen_srv.py
classhoster/main/hoster.py
classhoster/main/server.py
classhoster/main/start_hoster.py
classhoster/main/__pycache__/client.cpython-311.pyc
classhoster/main/__pycache__/gen_srv.cpython-311.pyc
classhoster/main/__pycache__/hoster.cpython-311.pyc
classhoster/main/__pycache__/server.cpython-311.pyc
classhoster/public/hostall.py
classhoster/public/hostclass.py
classhoster/public/loadclass.py
classhoster/public/robot_api.py
classhoster/public/systems.py
classhoster/public/__pycache__/hostall.cpython-311.pyc
classhoster/public/__pycache__/hostclass.cpython-311.pyc
classhoster/public/__pycache__/loadclass.cpython-311.pyc
classhoster/public/__pycache__/robot_api.cpython-311.pyc
classhoster/public/__pycache__/systems.cpython-311.pyc
classhoster/utility/__pycache__/__init__.cpython-311.pyc
classhoster/utility/logger/server_log.py
classhoster/utility/logger/__pycache__/server_log.cpython-311.pyc
classhoster/utility/tools/cmd_line_parser.py
classhoster/utility/tools/file_reader.py
classhoster/utility/tools/forker.py
classhoster/utility/tools/port_allocator.py
classhoster/utility/tools/timer.py
classhoster/utility/tools/__pycache__/cmd_line_parser.cpython-311.pyc
classhoster/utility/tools/__pycache__/file_reader.cpython-311.pyc
classhoster/utility/tools/__pycache__/forker.cpython-311.pyc
classhoster/utility/tools/__pycache__/port_allocator.cpython-311.pyc
classhoster/utility/tools/__pycache__/timer.cpython-311.pyc
classhoster/utility/types/defaults.py
classhoster/utility/types/req_resp.py
classhoster/utility/types/__pycache__/defaults.cpython-311.pyc
ClassHoster-0.1.5.dist-info/METADATA
ClassHoster-0.1.5.dist-info/WHEEL
ClassHoster-0.1.5.dist-info/entry_points.txt
ClassHoster-0.1.5.dist-info/top_level.txt
ClassHoster-0.1.5.dist-info/RECORD
