Metadata-Version: 2.1
Name: ClassHoster
Version: 0.1.5
Summary: Host ANY Class
Home-page: https://github.com/RepoFactory/ClassHoster
Author: Conner Sommerfield
Author-email: conner.sommerfield@gmail.com
Classifier: Programming Language :: Python :: 3
Classifier: License :: OSI Approved :: MIT License
Classifier: Operating System :: OS Independent
Requires-Python: >=3.8
